werkzeug/__init__.py
werkzeug/_internal.py
werkzeug/_reloader.py
werkzeug/exceptions.py
werkzeug/formparser.py
werkzeug/http.py
werkzeug/local.py
werkzeug/py.typed
werkzeug/security.py
werkzeug/serving.py
werkzeug/test.py
werkzeug/testapp.py
werkzeug/urls.py
werkzeug/user_agent.py
werkzeug/utils.py
werkzeug/wsgi.py
werkzeug/datastructures/__init__.py
werkzeug/datastructures/accept.py
werkzeug/datastructures/accept.pyi
werkzeug/datastructures/auth.py
werkzeug/datastructures/cache_control.py
werkzeug/datastructures/cache_control.pyi
werkzeug/datastructures/csp.py
werkzeug/datastructures/csp.pyi
werkzeug/datastructures/etag.py
werkzeug/datastructures/etag.pyi
werkzeug/datastructures/file_storage.py
werkzeug/datastructures/file_storage.pyi
werkzeug/datastructures/headers.py
werkzeug/datastructures/headers.pyi
werkzeug/datastructures/mixins.py
werkzeug/datastructures/mixins.pyi
werkzeug/datastructures/range.py
werkzeug/datastructures/range.pyi
werkzeug/datastructures/structures.py
werkzeug/datastructures/structures.pyi
werkzeug/debug/__init__.py
werkzeug/debug/console.py
werkzeug/debug/repr.py
werkzeug/debug/tbtools.py
werkzeug/debug/shared/ICON_LICENSE.md
werkzeug/debug/shared/console.png
werkzeug/debug/shared/debugger.js
werkzeug/debug/shared/less.png
werkzeug/debug/shared/more.png
werkzeug/debug/shared/style.css
werkzeug/middleware/__init__.py
werkzeug/middleware/dispatcher.py
werkzeug/middleware/http_proxy.py
werkzeug/middleware/lint.py
werkzeug/middleware/profiler.py
werkzeug/middleware/proxy_fix.py
werkzeug/middleware/shared_data.py
werkzeug/routing/__init__.py
werkzeug/routing/converters.py
werkzeug/routing/exceptions.py
werkzeug/routing/map.py
werkzeug/routing/matcher.py
werkzeug/routing/rules.py
werkzeug/sansio/__init__.py
werkzeug/sansio/http.py
werkzeug/sansio/multipart.py
werkzeug/sansio/request.py
werkzeug/sansio/response.py
werkzeug/sansio/utils.py
werkzeug/wrappers/__init__.py
werkzeug/wrappers/request.py
werkzeug/wrappers/response.py
Werkzeug_mireq-2.3.6.dist-info/LICENSE.rst
Werkzeug_mireq-2.3.6.dist-info/METADATA
Werkzeug_mireq-2.3.6.dist-info/WHEEL
Werkzeug_mireq-2.3.6.dist-info/top_level.txt
Werkzeug_mireq-2.3.6.dist-info/RECORD
