Metadata-Version: 2.1
Name: Werkzeug-mireq
Version: 2.3.6
Summary: The comprehensive WSGI web application library.
Maintainer-email: Pallets <contact@palletsprojects.com>
License: BSD-3-Clause
Project-URL: Donate, https://palletsprojects.com/donate
Project-URL: Documentation, https://werkzeug.palletsprojects.com/
Project-URL: Changes, https://werkzeug.palletsprojects.com/changes/
Project-URL: Source Code, https://github.com/mireq/werkzeug/
Project-URL: Issue Tracker, https://github.com/mireq/werkzeug/issues/
Project-URL: Chat, https://discord.gg/pallets
Classifier: Development Status :: 5 - Production/Stable
Classifier: Environment :: Web Environment
Classifier: Intended Audience :: Developers
Classifier: License :: OSI Approved :: BSD License
Classifier: Operating System :: OS Independent
Classifier: Programming Language :: Python
Classifier: Topic :: Internet :: WWW/HTTP :: Dynamic Content
Classifier: Topic :: Internet :: WWW/HTTP :: WSGI
Classifier: Topic :: Internet :: WWW/HTTP :: WSGI :: Application
Classifier: Topic :: Internet :: WWW/HTTP :: WSGI :: Middleware
Classifier: Topic :: Software Development :: Libraries :: Application Frameworks
Requires-Python: >=3.8
License-File: LICENSE.rst
Requires-Dist: MarkupSafe (>=2.1.1)
Provides-Extra: watchdog
Requires-Dist: watchdog (>=2.3) ; extra == 'watchdog'
